dodo/__init__.py
dodo/checker.py
dodo/commands.py
dodo/exporter.py
dodo/main.py
dodo/tlds.txt
dodo/utils.py
dodo_lookup-0.2.7.dist-info/licenses/LICENSE
dodo_lookup-0.2.7.dist-info/METADATA
dodo_lookup-0.2.7.dist-info/WHEEL
dodo_lookup-0.2.7.dist-info/entry_points.txt
dodo_lookup-0.2.7.dist-info/top_level.txt
dodo_lookup-0.2.7.dist-info/RECORD
