Metadata-Version: 2.4
Name: dodo-lookup
Version: 0.2.7
Summary: A minimal and colorful terminal tool to check domain availability across TLDs.
Home-page: https://github.com/OggyB/dodo
Author: Oguzhan Budak
Classifier: Programming Language :: Python :: 3
Classifier: Operating System :: OS Independent
Classifier: License :: OSI Approved :: MIT License
Classifier: Environment :: Console
Classifier: Topic :: Internet :: Name Service (DNS)
Requires-Python: >=3.7
License-File: LICENSE
Requires-Dist: python-whois
Requires-Dist: termcolor
Requires-Dist: pyfiglet
Requires-Dist: prettytable
Requires-Dist: tqdm
Dynamic: author
Dynamic: classifier
Dynamic: description
Dynamic: description-content-type
Dynamic: home-page
Dynamic: license-file
Dynamic: requires-dist
Dynamic: requires-python
Dynamic: summary
